spaghetti_code_zen/__init__.py
spaghetti_code_zen-1.2.0.dist-info/licenses/LICENSE
spaghetti_code_zen-1.2.0.dist-info/METADATA
spaghetti_code_zen-1.2.0.dist-info/WHEEL
spaghetti_code_zen-1.2.0.dist-info/top_level.txt
spaghetti_code_zen-1.2.0.dist-info/RECORD
